{
  "ok": true,
  "source": "OPCOM PZU / ROPEX_DAM_15min",
  "sourceMode": "external-cache-github",
  "currency": "Lei/MWh",
  "granularity": "15m",
  "intervals": 96,
  "min": 131,
  "max": 1150,
  "avg": 638,
  "records": [
    {
      "interval": 1,
      "i": 0,
      "hour": 0,
      "label": "00:00",
      "price": 915,
      "priceLeiMwh": 915,
      "rawPriceLeiMwh": 914.88,
      "source": "OPCOM PZU / ROPEX_DAM_15min"
    },
    {
      "interval": 2,
      "i": 1,
      "hour": 0.25,
      "label": "00:15",
      "price": 893,
      "priceLeiMwh": 893,
      "rawPriceLeiMwh": 892.97,
      "source": "OPCOM PZU / ROPEX_DAM_15min"
    },
    {
      "interval": 3,
      "i": 2,
      "hour": 0.5,
      "label": "00:30",
      "price": 797,
      "priceLeiMwh": 797,
      "rawPriceLeiMwh": 796.83,
      "source": "OPCOM PZU / ROPEX_DAM_15min"
    },
    {
      "interval": 4,
      "i": 3,
      "hour": 0.75,
      "label": "00:45",
      "price": 766,
      "priceLeiMwh": 766,
      "rawPriceLeiMwh": 766.36,
      "source": "OPCOM PZU / ROPEX_DAM_15min"
    },
    {
      "interval": 5,
      "i": 4,
      "hour": 1,
      "label": "01:00",
      "price": 826,
      "priceLeiMwh": 826,
      "rawPriceLeiMwh": 825.61,
      "source": "OPCOM PZU / ROPEX_DAM_15min"
    },
    {
      "interval": 6,
      "i": 5,
      "hour": 1.25,
      "label": "01:15",
      "price": 786,
      "priceLeiMwh": 786,
      "rawPriceLeiMwh": 785.73,
      "source": "OPCOM PZU / ROPEX_DAM_15min"
    },
    {
      "interval": 7,
      "i": 6,
      "hour": 1.5,
      "label": "01:30",
      "price": 788,
      "priceLeiMwh": 788,
      "rawPriceLeiMwh": 788.31,
      "source": "OPCOM PZU / ROPEX_DAM_15min"
    },
    {
      "interval": 8,
      "i": 7,
      "hour": 1.75,
      "label": "01:45",
      "price": 751,
      "priceLeiMwh": 751,
      "rawPriceLeiMwh": 750.92,
      "source": "OPCOM PZU / ROPEX_DAM_15min"
    },
    {
      "interval": 9,
      "i": 8,
      "hour": 2,
      "label": "02:00",
      "price": 861,
      "priceLeiMwh": 861,
      "rawPriceLeiMwh": 861.42,
      "source": "OPCOM PZU / ROPEX_DAM_15min"
    },
    {
      "interval": 10,
      "i": 9,
      "hour": 2.25,
      "label": "02:15",
      "price": 826,
      "priceLeiMwh": 826,
      "rawPriceLeiMwh": 825.7,
      "source": "OPCOM PZU / ROPEX_DAM_15min"
    },
    {
      "interval": 11,
      "i": 10,
      "hour": 2.5,
      "label": "02:30",
      "price": 789,
      "priceLeiMwh": 789,
      "rawPriceLeiMwh": 789.38,
      "source": "OPCOM PZU / ROPEX_DAM_15min"
    },
    {
      "interval": 12,
      "i": 11,
      "hour": 2.75,
      "label": "02:45",
      "price": 743,
      "priceLeiMwh": 743,
      "rawPriceLeiMwh": 742.64,
      "source": "OPCOM PZU / ROPEX_DAM_15min"
    },
    {
      "interval": 13,
      "i": 12,
      "hour": 3,
      "label": "03:00",
      "price": 776,
      "priceLeiMwh": 776,
      "rawPriceLeiMwh": 775.51,
      "source": "OPCOM PZU / ROPEX_DAM_15min"
    },
    {
      "interval": 14,
      "i": 13,
      "hour": 3.25,
      "label": "03:15",
      "price": 711,
      "priceLeiMwh": 711,
      "rawPriceLeiMwh": 710.51,
      "source": "OPCOM PZU / ROPEX_DAM_15min"
    },
    {
      "interval": 15,
      "i": 14,
      "hour": 3.5,
      "label": "03:30",
      "price": 696,
      "priceLeiMwh": 696,
      "rawPriceLeiMwh": 695.71,
      "source": "OPCOM PZU / ROPEX_DAM_15min"
    },
    {
      "interval": 16,
      "i": 15,
      "hour": 3.75,
      "label": "03:45",
      "price": 689,
      "priceLeiMwh": 689,
      "rawPriceLeiMwh": 689.07,
      "source": "OPCOM PZU / ROPEX_DAM_15min"
    },
    {
      "interval": 17,
      "i": 16,
      "hour": 4,
      "label": "04:00",
      "price": 687,
      "priceLeiMwh": 687,
      "rawPriceLeiMwh": 686.88,
      "source": "OPCOM PZU / ROPEX_DAM_15min"
    },
    {
      "interval": 18,
      "i": 17,
      "hour": 4.25,
      "label": "04:15",
      "price": 684,
      "priceLeiMwh": 684,
      "rawPriceLeiMwh": 684.22,
      "source": "OPCOM PZU / ROPEX_DAM_15min"
    },
    {
      "interval": 19,
      "i": 18,
      "hour": 4.5,
      "label": "04:30",
      "price": 691,
      "priceLeiMwh": 691,
      "rawPriceLeiMwh": 691,
      "source": "OPCOM PZU / ROPEX_DAM_15min"
    },
    {
      "interval": 20,
      "i": 19,
      "hour": 4.75,
      "label": "04:45",
      "price": 694,
      "priceLeiMwh": 694,
      "rawPriceLeiMwh": 694.11,
      "source": "OPCOM PZU / ROPEX_DAM_15min"
    },
    {
      "interval": 21,
      "i": 20,
      "hour": 5,
      "label": "05:00",
      "price": 703,
      "priceLeiMwh": 703,
      "rawPriceLeiMwh": 703.48,
      "source": "OPCOM PZU / ROPEX_DAM_15min"
    },
    {
      "interval": 22,
      "i": 21,
      "hour": 5.25,
      "label": "05:15",
      "price": 743,
      "priceLeiMwh": 743,
      "rawPriceLeiMwh": 743.11,
      "source": "OPCOM PZU / ROPEX_DAM_15min"
    },
    {
      "interval": 23,
      "i": 22,
      "hour": 5.5,
      "label": "05:30",
      "price": 762,
      "priceLeiMwh": 762,
      "rawPriceLeiMwh": 761.93,
      "source": "OPCOM PZU / ROPEX_DAM_15min"
    },
    {
      "interval": 24,
      "i": 23,
      "hour": 5.75,
      "label": "05:45",
      "price": 791,
      "priceLeiMwh": 791,
      "rawPriceLeiMwh": 791.49,
      "source": "OPCOM PZU / ROPEX_DAM_15min"
    },
    {
      "interval": 25,
      "i": 24,
      "hour": 6,
      "label": "06:00",
      "price": 797,
      "priceLeiMwh": 797,
      "rawPriceLeiMwh": 796.6,
      "source": "OPCOM PZU / ROPEX_DAM_15min"
    },
    {
      "interval": 26,
      "i": 25,
      "hour": 6.25,
      "label": "06:15",
      "price": 815,
      "priceLeiMwh": 815,
      "rawPriceLeiMwh": 815.29,
      "source": "OPCOM PZU / ROPEX_DAM_15min"
    },
    {
      "interval": 27,
      "i": 26,
      "hour": 6.5,
      "label": "06:30",
      "price": 842,
      "priceLeiMwh": 842,
      "rawPriceLeiMwh": 841.75,
      "source": "OPCOM PZU / ROPEX_DAM_15min"
    },
    {
      "interval": 28,
      "i": 27,
      "hour": 6.75,
      "label": "06:45",
      "price": 782,
      "priceLeiMwh": 782,
      "rawPriceLeiMwh": 782.32,
      "source": "OPCOM PZU / ROPEX_DAM_15min"
    },
    {
      "interval": 29,
      "i": 28,
      "hour": 7,
      "label": "07:00",
      "price": 906,
      "priceLeiMwh": 906,
      "rawPriceLeiMwh": 906.41,
      "source": "OPCOM PZU / ROPEX_DAM_15min"
    },
    {
      "interval": 30,
      "i": 29,
      "hour": 7.25,
      "label": "07:15",
      "price": 852,
      "priceLeiMwh": 852,
      "rawPriceLeiMwh": 851.52,
      "source": "OPCOM PZU / ROPEX_DAM_15min"
    },
    {
      "interval": 31,
      "i": 30,
      "hour": 7.5,
      "label": "07:30",
      "price": 713,
      "priceLeiMwh": 713,
      "rawPriceLeiMwh": 712.58,
      "source": "OPCOM PZU / ROPEX_DAM_15min"
    },
    {
      "interval": 32,
      "i": 31,
      "hour": 7.75,
      "label": "07:45",
      "price": 631,
      "priceLeiMwh": 631,
      "rawPriceLeiMwh": 631.05,
      "source": "OPCOM PZU / ROPEX_DAM_15min"
    },
    {
      "interval": 33,
      "i": 32,
      "hour": 8,
      "label": "08:00",
      "price": 902,
      "priceLeiMwh": 902,
      "rawPriceLeiMwh": 901.91,
      "source": "OPCOM PZU / ROPEX_DAM_15min"
    },
    {
      "interval": 34,
      "i": 33,
      "hour": 8.25,
      "label": "08:15",
      "price": 803,
      "priceLeiMwh": 803,
      "rawPriceLeiMwh": 803.16,
      "source": "OPCOM PZU / ROPEX_DAM_15min"
    },
    {
      "interval": 35,
      "i": 34,
      "hour": 8.5,
      "label": "08:30",
      "price": 653,
      "priceLeiMwh": 653,
      "rawPriceLeiMwh": 652.72,
      "source": "OPCOM PZU / ROPEX_DAM_15min"
    },
    {
      "interval": 36,
      "i": 35,
      "hour": 8.75,
      "label": "08:45",
      "price": 576,
      "priceLeiMwh": 576,
      "rawPriceLeiMwh": 576.43,
      "source": "OPCOM PZU / ROPEX_DAM_15min"
    },
    {
      "interval": 37,
      "i": 36,
      "hour": 9,
      "label": "09:00",
      "price": 661,
      "priceLeiMwh": 661,
      "rawPriceLeiMwh": 661.46,
      "source": "OPCOM PZU / ROPEX_DAM_15min"
    },
    {
      "interval": 38,
      "i": 37,
      "hour": 9.25,
      "label": "09:15",
      "price": 608,
      "priceLeiMwh": 608,
      "rawPriceLeiMwh": 607.75,
      "source": "OPCOM PZU / ROPEX_DAM_15min"
    },
    {
      "interval": 39,
      "i": 38,
      "hour": 9.5,
      "label": "09:30",
      "price": 506,
      "priceLeiMwh": 506,
      "rawPriceLeiMwh": 505.96,
      "source": "OPCOM PZU / ROPEX_DAM_15min"
    },
    {
      "interval": 40,
      "i": 39,
      "hour": 9.75,
      "label": "09:45",
      "price": 343,
      "priceLeiMwh": 343,
      "rawPriceLeiMwh": 343,
      "source": "OPCOM PZU / ROPEX_DAM_15min"
    },
    {
      "interval": 41,
      "i": 40,
      "hour": 10,
      "label": "10:00",
      "price": 524,
      "priceLeiMwh": 524,
      "rawPriceLeiMwh": 524.07,
      "source": "OPCOM PZU / ROPEX_DAM_15min"
    },
    {
      "interval": 42,
      "i": 41,
      "hour": 10.25,
      "label": "10:15",
      "price": 458,
      "priceLeiMwh": 458,
      "rawPriceLeiMwh": 457.97,
      "source": "OPCOM PZU / ROPEX_DAM_15min"
    },
    {
      "interval": 43,
      "i": 42,
      "hour": 10.5,
      "label": "10:30",
      "price": 367,
      "priceLeiMwh": 367,
      "rawPriceLeiMwh": 367.15,
      "source": "OPCOM PZU / ROPEX_DAM_15min"
    },
    {
      "interval": 44,
      "i": 43,
      "hour": 10.75,
      "label": "10:45",
      "price": 258,
      "priceLeiMwh": 258,
      "rawPriceLeiMwh": 257.55,
      "source": "OPCOM PZU / ROPEX_DAM_15min"
    },
    {
      "interval": 45,
      "i": 44,
      "hour": 11,
      "label": "11:00",
      "price": 256,
      "priceLeiMwh": 256,
      "rawPriceLeiMwh": 255.8,
      "source": "OPCOM PZU / ROPEX_DAM_15min"
    },
    {
      "interval": 46,
      "i": 45,
      "hour": 11.25,
      "label": "11:15",
      "price": 251,
      "priceLeiMwh": 251,
      "rawPriceLeiMwh": 251.39,
      "source": "OPCOM PZU / ROPEX_DAM_15min"
    },
    {
      "interval": 47,
      "i": 46,
      "hour": 11.5,
      "label": "11:30",
      "price": 312,
      "priceLeiMwh": 312,
      "rawPriceLeiMwh": 311.88,
      "source": "OPCOM PZU / ROPEX_DAM_15min"
    },
    {
      "interval": 48,
      "i": 47,
      "hour": 11.75,
      "label": "11:45",
      "price": 280,
      "priceLeiMwh": 280,
      "rawPriceLeiMwh": 279.88,
      "source": "OPCOM PZU / ROPEX_DAM_15min"
    },
    {
      "interval": 49,
      "i": 48,
      "hour": 12,
      "label": "12:00",
      "price": 241,
      "priceLeiMwh": 241,
      "rawPriceLeiMwh": 240.83,
      "source": "OPCOM PZU / ROPEX_DAM_15min"
    },
    {
      "interval": 50,
      "i": 49,
      "hour": 12.25,
      "label": "12:15",
      "price": 292,
      "priceLeiMwh": 292,
      "rawPriceLeiMwh": 291.67,
      "source": "OPCOM PZU / ROPEX_DAM_15min"
    },
    {
      "interval": 51,
      "i": 50,
      "hour": 12.5,
      "label": "12:30",
      "price": 251,
      "priceLeiMwh": 251,
      "rawPriceLeiMwh": 250.73,
      "source": "OPCOM PZU / ROPEX_DAM_15min"
    },
    {
      "interval": 52,
      "i": 51,
      "hour": 12.75,
      "label": "12:45",
      "price": 265,
      "priceLeiMwh": 265,
      "rawPriceLeiMwh": 264.77,
      "source": "OPCOM PZU / ROPEX_DAM_15min"
    },
    {
      "interval": 53,
      "i": 52,
      "hour": 13,
      "label": "13:00",
      "price": 295,
      "priceLeiMwh": 295,
      "rawPriceLeiMwh": 295.22,
      "source": "OPCOM PZU / ROPEX_DAM_15min"
    },
    {
      "interval": 54,
      "i": 53,
      "hour": 13.25,
      "label": "13:15",
      "price": 287,
      "priceLeiMwh": 287,
      "rawPriceLeiMwh": 286.73,
      "source": "OPCOM PZU / ROPEX_DAM_15min"
    },
    {
      "interval": 55,
      "i": 54,
      "hour": 13.5,
      "label": "13:30",
      "price": 275,
      "priceLeiMwh": 275,
      "rawPriceLeiMwh": 274.89,
      "source": "OPCOM PZU / ROPEX_DAM_15min"
    },
    {
      "interval": 56,
      "i": 55,
      "hour": 13.75,
      "label": "13:45",
      "price": 237,
      "priceLeiMwh": 237,
      "rawPriceLeiMwh": 236.89,
      "source": "OPCOM PZU / ROPEX_DAM_15min"
    },
    {
      "interval": 57,
      "i": 56,
      "hour": 14,
      "label": "14:00",
      "price": 256,
      "priceLeiMwh": 256,
      "rawPriceLeiMwh": 256.23,
      "source": "OPCOM PZU / ROPEX_DAM_15min"
    },
    {
      "interval": 58,
      "i": 57,
      "hour": 14.25,
      "label": "14:15",
      "price": 208,
      "priceLeiMwh": 208,
      "rawPriceLeiMwh": 207.65,
      "source": "OPCOM PZU / ROPEX_DAM_15min"
    },
    {
      "interval": 59,
      "i": 58,
      "hour": 14.5,
      "label": "14:30",
      "price": 250,
      "priceLeiMwh": 250,
      "rawPriceLeiMwh": 250.04,
      "source": "OPCOM PZU / ROPEX_DAM_15min"
    },
    {
      "interval": 60,
      "i": 59,
      "hour": 14.75,
      "label": "14:45",
      "price": 286,
      "priceLeiMwh": 286,
      "rawPriceLeiMwh": 285.94,
      "source": "OPCOM PZU / ROPEX_DAM_15min"
    },
    {
      "interval": 61,
      "i": 60,
      "hour": 15,
      "label": "15:00",
      "price": 216,
      "priceLeiMwh": 216,
      "rawPriceLeiMwh": 215.68,
      "source": "OPCOM PZU / ROPEX_DAM_15min"
    },
    {
      "interval": 62,
      "i": 61,
      "hour": 15.25,
      "label": "15:15",
      "price": 253,
      "priceLeiMwh": 253,
      "rawPriceLeiMwh": 252.54,
      "source": "OPCOM PZU / ROPEX_DAM_15min"
    },
    {
      "interval": 63,
      "i": 62,
      "hour": 15.5,
      "label": "15:30",
      "price": 251,
      "priceLeiMwh": 251,
      "rawPriceLeiMwh": 251.49,
      "source": "OPCOM PZU / ROPEX_DAM_15min"
    },
    {
      "interval": 64,
      "i": 63,
      "hour": 15.75,
      "label": "15:45",
      "price": 320,
      "priceLeiMwh": 320,
      "rawPriceLeiMwh": 319.9,
      "source": "OPCOM PZU / ROPEX_DAM_15min"
    },
    {
      "interval": 65,
      "i": 64,
      "hour": 16,
      "label": "16:00",
      "price": 192,
      "priceLeiMwh": 192,
      "rawPriceLeiMwh": 191.99,
      "source": "OPCOM PZU / ROPEX_DAM_15min"
    },
    {
      "interval": 66,
      "i": 65,
      "hour": 16.25,
      "label": "16:15",
      "price": 345,
      "priceLeiMwh": 345,
      "rawPriceLeiMwh": 344.91,
      "source": "OPCOM PZU / ROPEX_DAM_15min"
    },
    {
      "interval": 67,
      "i": 66,
      "hour": 16.5,
      "label": "16:30",
      "price": 337,
      "priceLeiMwh": 337,
      "rawPriceLeiMwh": 336.5,
      "source": "OPCOM PZU / ROPEX_DAM_15min"
    },
    {
      "interval": 68,
      "i": 67,
      "hour": 16.75,
      "label": "16:45",
      "price": 558,
      "priceLeiMwh": 558,
      "rawPriceLeiMwh": 558.04,
      "source": "OPCOM PZU / ROPEX_DAM_15min"
    },
    {
      "interval": 69,
      "i": 68,
      "hour": 17,
      "label": "17:00",
      "price": 131,
      "priceLeiMwh": 131,
      "rawPriceLeiMwh": 131.01,
      "source": "OPCOM PZU / ROPEX_DAM_15min"
    },
    {
      "interval": 70,
      "i": 69,
      "hour": 17.25,
      "label": "17:15",
      "price": 553,
      "priceLeiMwh": 553,
      "rawPriceLeiMwh": 552.86,
      "source": "OPCOM PZU / ROPEX_DAM_15min"
    },
    {
      "interval": 71,
      "i": 70,
      "hour": 17.5,
      "label": "17:30",
      "price": 744,
      "priceLeiMwh": 744,
      "rawPriceLeiMwh": 743.53,
      "source": "OPCOM PZU / ROPEX_DAM_15min"
    },
    {
      "interval": 72,
      "i": 71,
      "hour": 17.75,
      "label": "17:45",
      "price": 881,
      "priceLeiMwh": 881,
      "rawPriceLeiMwh": 880.8,
      "source": "OPCOM PZU / ROPEX_DAM_15min"
    },
    {
      "interval": 73,
      "i": 72,
      "hour": 18,
      "label": "18:00",
      "price": 625,
      "priceLeiMwh": 625,
      "rawPriceLeiMwh": 624.73,
      "source": "OPCOM PZU / ROPEX_DAM_15min"
    },
    {
      "interval": 74,
      "i": 73,
      "hour": 18.25,
      "label": "18:15",
      "price": 682,
      "priceLeiMwh": 682,
      "rawPriceLeiMwh": 681.66,
      "source": "OPCOM PZU / ROPEX_DAM_15min"
    },
    {
      "interval": 75,
      "i": 74,
      "hour": 18.5,
      "label": "18:30",
      "price": 766,
      "priceLeiMwh": 766,
      "rawPriceLeiMwh": 765.97,
      "source": "OPCOM PZU / ROPEX_DAM_15min"
    },
    {
      "interval": 76,
      "i": 75,
      "hour": 18.75,
      "label": "18:45",
      "price": 808,
      "priceLeiMwh": 808,
      "rawPriceLeiMwh": 807.51,
      "source": "OPCOM PZU / ROPEX_DAM_15min"
    },
    {
      "interval": 77,
      "i": 76,
      "hour": 19,
      "label": "19:00",
      "price": 747,
      "priceLeiMwh": 747,
      "rawPriceLeiMwh": 746.8,
      "source": "OPCOM PZU / ROPEX_DAM_15min"
    },
    {
      "interval": 78,
      "i": 77,
      "hour": 19.25,
      "label": "19:15",
      "price": 865,
      "priceLeiMwh": 865,
      "rawPriceLeiMwh": 865.41,
      "source": "OPCOM PZU / ROPEX_DAM_15min"
    },
    {
      "interval": 79,
      "i": 78,
      "hour": 19.5,
      "label": "19:30",
      "price": 961,
      "priceLeiMwh": 961,
      "rawPriceLeiMwh": 960.72,
      "source": "OPCOM PZU / ROPEX_DAM_15min"
    },
    {
      "interval": 80,
      "i": 79,
      "hour": 19.75,
      "label": "19:45",
      "price": 1015,
      "priceLeiMwh": 1015,
      "rawPriceLeiMwh": 1015.35,
      "source": "OPCOM PZU / ROPEX_DAM_15min"
    },
    {
      "interval": 81,
      "i": 80,
      "hour": 20,
      "label": "20:00",
      "price": 990,
      "priceLeiMwh": 990,
      "rawPriceLeiMwh": 989.7,
      "source": "OPCOM PZU / ROPEX_DAM_15min"
    },
    {
      "interval": 82,
      "i": 81,
      "hour": 20.25,
      "label": "20:15",
      "price": 1150,
      "priceLeiMwh": 1150,
      "rawPriceLeiMwh": 1150,
      "source": "OPCOM PZU / ROPEX_DAM_15min"
    },
    {
      "interval": 83,
      "i": 82,
      "hour": 20.5,
      "label": "20:30",
      "price": 1150,
      "priceLeiMwh": 1150,
      "rawPriceLeiMwh": 1150,
      "source": "OPCOM PZU / ROPEX_DAM_15min"
    },
    {
      "interval": 84,
      "i": 83,
      "hour": 20.75,
      "label": "20:45",
      "price": 1106,
      "priceLeiMwh": 1106,
      "rawPriceLeiMwh": 1106.26,
      "source": "OPCOM PZU / ROPEX_DAM_15min"
    },
    {
      "interval": 85,
      "i": 84,
      "hour": 21,
      "label": "21:00",
      "price": 892,
      "priceLeiMwh": 892,
      "rawPriceLeiMwh": 892.36,
      "source": "OPCOM PZU / ROPEX_DAM_15min"
    },
    {
      "interval": 86,
      "i": 85,
      "hour": 21.25,
      "label": "21:15",
      "price": 863,
      "priceLeiMwh": 863,
      "rawPriceLeiMwh": 863.25,
      "source": "OPCOM PZU / ROPEX_DAM_15min"
    },
    {
      "interval": 87,
      "i": 86,
      "hour": 21.5,
      "label": "21:30",
      "price": 867,
      "priceLeiMwh": 867,
      "rawPriceLeiMwh": 866.89,
      "source": "OPCOM PZU / ROPEX_DAM_15min"
    },
    {
      "interval": 88,
      "i": 87,
      "hour": 21.75,
      "label": "21:45",
      "price": 839,
      "priceLeiMwh": 839,
      "rawPriceLeiMwh": 838.57,
      "source": "OPCOM PZU / ROPEX_DAM_15min"
    },
    {
      "interval": 89,
      "i": 88,
      "hour": 22,
      "label": "22:00",
      "price": 904,
      "priceLeiMwh": 904,
      "rawPriceLeiMwh": 904.37,
      "source": "OPCOM PZU / ROPEX_DAM_15min"
    },
    {
      "interval": 90,
      "i": 89,
      "hour": 22.25,
      "label": "22:15",
      "price": 861,
      "priceLeiMwh": 861,
      "rawPriceLeiMwh": 860.85,
      "source": "OPCOM PZU / ROPEX_DAM_15min"
    },
    {
      "interval": 91,
      "i": 90,
      "hour": 22.5,
      "label": "22:30",
      "price": 846,
      "priceLeiMwh": 846,
      "rawPriceLeiMwh": 845.86,
      "source": "OPCOM PZU / ROPEX_DAM_15min"
    },
    {
      "interval": 92,
      "i": 91,
      "hour": 22.75,
      "label": "22:45",
      "price": 806,
      "priceLeiMwh": 806,
      "rawPriceLeiMwh": 805.77,
      "source": "OPCOM PZU / ROPEX_DAM_15min"
    },
    {
      "interval": 93,
      "i": 92,
      "hour": 23,
      "label": "23:00",
      "price": 839,
      "priceLeiMwh": 839,
      "rawPriceLeiMwh": 838.59,
      "source": "OPCOM PZU / ROPEX_DAM_15min"
    },
    {
      "interval": 94,
      "i": 93,
      "hour": 23.25,
      "label": "23:15",
      "price": 780,
      "priceLeiMwh": 780,
      "rawPriceLeiMwh": 780.01,
      "source": "OPCOM PZU / ROPEX_DAM_15min"
    },
    {
      "interval": 95,
      "i": 94,
      "hour": 23.5,
      "label": "23:30",
      "price": 771,
      "priceLeiMwh": 771,
      "rawPriceLeiMwh": 771.43,
      "source": "OPCOM PZU / ROPEX_DAM_15min"
    },
    {
      "interval": 96,
      "i": 95,
      "hour": 23.75,
      "label": "23:45",
      "price": 720,
      "priceLeiMwh": 720,
      "rawPriceLeiMwh": 720.19,
      "source": "OPCOM PZU / ROPEX_DAM_15min"
    }
  ],
  "deliveryDay": "2026-07-22",
  "sourceUrl": "https://www.opcom.ro/rapoarte-pzu-raportPIP-export-csv/22/7/2026/ro",
  "pageUrl": "https://www.opcom.ro/grafice-ip-raportPIP-si-volumTranzactionat/ro",
  "updatedAtUtc": "2026-07-22T11:18:59.425Z",
  "generatedBy": "GitHub Actions / scripts/fetch-opcom-pzu-cache.mjs"
}
